signet_sdk/__init__.py
signet_sdk/verify.py
signet_sdk-0.1.0.dist-info/licenses/LICENSE
signet_sdk-0.1.0.dist-info/METADATA
signet_sdk-0.1.0.dist-info/WHEEL
signet_sdk-0.1.0.dist-info/top_level.txt
signet_sdk-0.1.0.dist-info/RECORD
