Metadata-Version: 2.4
Name: signet-sdk
Version: 0.1.0
Summary: Signet Protocol Python SDK (receipt & STH verification)
Author: Signet
License: Apache-2.0
Project-URL: Homepage, https://github.com/Maverick0351a/SignetProtocolMVP
Keywords: signet,receipts,merkle,ed25519,provenance
Classifier: Programming Language :: Python :: 3
Classifier: Programming Language :: Python :: 3.11
Classifier: Programming Language :: Python :: 3.12
Classifier: License :: OSI Approved :: Apache Software License
Classifier: Operating System :: OS Independent
Requires-Python: >=3.11
License-File: LICENSE
Requires-Dist: rfc8785==0.1.4
Requires-Dist: PyNaCl==1.5.0
Provides-Extra: dev
Requires-Dist: pytest; extra == "dev"
Requires-Dist: ruff; extra == "dev"
Dynamic: license-file
